<?xml version="1.0" encoding="utf-8"?>
<!DOCTYPE hibernate-mapping PUBLIC "-//Hibernate/Hibernate Mapping DTD 3.0//EN"
                                   "http://hibernate.sourceforge.net/hibernate-mapping-3.0.dtd">
<!-- 
    Mapping file autogenerated by MyEclipse Persistence Tools
-->
<hibernate-mapping>
 <class name="domain.MappingToolH" table="com_fpdsavills_pr_mappingtool">
  <composite-id class="domain.ID" mapped="false" name="ID" unsaved-value="undefined">
   <key-property column="ID" name="identifier" type="java.lang.Long"/>
  </composite-id>
  <property generated="never" lazy="false" name="entityName" type="java.lang.String">
   <column name="EntityName"/>
  </property>
  <property generated="never" lazy="false" name="internalValue" type="java.lang.String">
   <column name="internalValue_"/>
  </property>
  <property generated="never" lazy="false" name="externalValue" type="java.lang.String">
   <column name="externalValue_"/>
  </property>
  <property generated="never" lazy="false" name="attributeName" type="java.lang.String">
   <column name="attributeName_"/>
  </property>
 </class>
</hibernate-mapping>
